[{"nome":"FC Haka","escudo":"escudos/fi/FCHaka-m.jpg","pais":"FI"},{"nome":"FC Honka Espoo","escudo":"escudos/fi/FCHonkaEspoo-m.jpg","pais":"FI"},{"nome":"FC Inter Turku","escudo":"escudos/fi/FCInterTurku-m.jpg","pais":"FI"},{"nome":"FC Lahti","escudo":"escudos/fi/FCLahti-m.jpg","pais":"FI"},{"nome":"FF Jaro","escudo":"escudos/fi/FFJaro-m.jpg","pais":"FI"},{"nome":"Helsingin Jalkapalloklubi","escudo":"escudos/fi/HelsinginJalkapalloklubi-m.jpg","pais":"FI"},{"nome":"IFK Mariehamn","escudo":"escudos/fi/IFKMariehamn-m.jpg","pais":"FI"},{"nome":"JJK Jyvaskyla","escudo":"escudos/fi/JJKJyvaskyla-m.jpg","pais":"FI"},{"nome":"KuPS (Kuopion Palloseura)","escudo":"escudos/fi/KuPS(KuopionPalloseura)-m.jpg","pais":"FI"},{"nome":"MYPA","escudo":"escudos/fi/MYPA-m.jpg","pais":"FI"},{"nome":"Turun Palloseura","escudo":"escudos/fi/TurunPalloseura-m.jpg","pais":"FI"},{"nome":"VPS (Vaasan Palloseura)","escudo":"escudos/fi/VPS(VaasanPalloseura)-m.jpg","pais":"FI"},{"nome":"Veikkausliiga","escudo":"escudos/fi/Veikkausliiga-m.jpg","pais":"FI"}]